nanosaur/__init__.py
nanosaur/docker.py
nanosaur/logger_config.py
nanosaur/main.py
nanosaur/prompt_colors.py
nanosaur/robot.py
nanosaur/ros.py
nanosaur/simulation.py
nanosaur/swarm.py
nanosaur/utilities.py
nanosaur/variables.py
nanosaur/workspace.py
nanosaur-0.1.4.dist-info/LICENSE
nanosaur-0.1.4.dist-info/METADATA
nanosaur-0.1.4.dist-info/WHEEL
nanosaur-0.1.4.dist-info/entry_points.txt
nanosaur-0.1.4.dist-info/top_level.txt
nanosaur-0.1.4.dist-info/RECORD
