Metadata-Version: 2.2
Name: nanosaur
Version: 0.1.4
Summary: A nanosaur package
Author-email: Raffaello Bonghi <raffaello@rnext.it>
License: MIT License
Project-URL: homepage, https://nanosaur.ai
Project-URL: documentation, https://docs.example.com
Project-URL: repository, https://github.com/rnanousaur/nanosaur
Classifier: Programming Language :: Python :: 3
Classifier: License :: OSI Approved :: MIT License
Classifier: Operating System :: OS Independent
Requires-Python: >=3.8
License-File: LICENSE
Requires-Dist: inquirer
Requires-Dist: gitpython
Requires-Dist: argcomplete
Requires-Dist: pyyaml
Requires-Dist: pexpect
Requires-Dist: requests
Requires-Dist: python-on-whales
Requires-Dist: jetson-stats
Requires-Dist: packaging
Provides-Extra: dev
Requires-Dist: catkin_pkg; extra == "dev"
Requires-Dist: empy==3.3.4; extra == "dev"
Requires-Dist: lark; extra == "dev"
Requires-Dist: flake8; extra == "dev"
